AUTHORS
MANIFEST.in
README.rst
setup.py
django_zodb/__init__.py
django_zodb/config.py
django_zodb/database.py
django_zodb/middleware.py
django_zodb/models.py
django_zodb/utils.py
django_zodb/version.py
django_zodb/views.py
django_zodb.egg-info/PKG-INFO
django_zodb.egg-info/SOURCES.txt
django_zodb.egg-info/dependency_links.txt
django_zodb.egg-info/requires.txt
django_zodb.egg-info/top_level.txt
django_zodb/management/__init__.py
django_zodb/management/commands/__init__.py
django_zodb/management/commands/zshell.py
django_zodb/storage/__init__.py
django_zodb/storage/base.py
django_zodb/storage/mysql.py
django_zodb/storage/oracle.py
django_zodb/storage/postgresql.py
django_zodb/storage/rdbms.py
django_zodb/storage/zeo.py
samples/__init__.py
samples/wiki/__init__.py
samples/wiki/forms.py
samples/wiki/models.py
samples/wiki/urls.py
samples/wiki/views.py
tests/__init__.py
tests/__init__.pyc
tests/models.py
tests/models.pyc
tests/test_database.py
tests/test_database.pyc
tests/test_models.py
tests/test_models.pyc
tests/test_storage.py
tests/test_storage.pyc
tests/test_utils.py
tests/test_utils.pyc
tests/test_views.py
tests/test_views.pyc
tests/tests.py
tests/tests.pyc
testutils/__init__.py
testutils/django_coverage.py
testutils/tools.py