Metadata-Version: 1.0
Name: django-zodb
Version: 0.2
Summary: Using Django and ZODB together
Home-page: http://triveos.github.com/django-zodb/
Author: Osvaldo Santana Neto
Author-email: osantana@triveos.com
License: BSD
Download-URL: http://github.com/triveos/django-zodb/downloads
Platform: UNKNOWN
Classifier: Environment :: Web Environment
Classifier: Development Status :: 4 - Beta
Classifier: Framework :: Django
Classifier: Intended Audience :: Developers
Classifier: License :: OSI Approved :: BSD License
Classifier: Operating System :: OS Independent
Classifier: Programming Language :: Python
Classifier: Topic :: Utilities
Classifier: Topic :: Software Development :: Libraries :: Python Modules
